uplot/__init__.py
uplot/color_picker.py
uplot/exceptions.py
uplot/generate_html.py
uplot/plot.py
uplot/plot2.py
uplot/utils.py
uplot/write_html_tempfile.py
uplot/static/__init__.py
uplot/static/uPlot.iife.js
uplot/static/uPlot.min.css
uplot/static/uPlot.mousewheel.js
uplot_python-1.0.0.dist-info/LICENSE
uplot_python-1.0.0.dist-info/WHEEL
uplot_python-1.0.0.dist-info/METADATA
uplot_python-1.0.0.dist-info/RECORD
